filesystem_server/__init__.py
filesystem_server/server.py
mcp_filesystem_server-0.2.0.dist-info/licenses/LICENSE
mcp_filesystem_server-0.2.0.dist-info/METADATA
mcp_filesystem_server-0.2.0.dist-info/WHEEL
mcp_filesystem_server-0.2.0.dist-info/entry_points.txt
mcp_filesystem_server-0.2.0.dist-info/top_level.txt
mcp_filesystem_server-0.2.0.dist-info/RECORD
