Metadata-Version: 2.4
Name: mcp-filesystem-server
Version: 0.2.0
Summary: MCP server for filesystem operations with advanced features
Author-email: Vamsi <vamsiindugu@gmail.com>
License: MIT License
Project-URL: Homepage, https://github.com/Vamsiindugu/mcp-filesystem-server
Project-URL: Repository, https://github.com/Vamsiindugu/mcp-filesystem-server
Requires-Python: >=3.10
License-File: LICENSE
Requires-Dist: mcp-server
Requires-Dist: chardet
Requires-Dist: watchdog
Dynamic: license-file
